dotprmpt-0.1.0.dist-info/licenses/LICENSE
prmpt/__init__.py
prmpt/canonical.py
prmpt/cli.py
prmpt/contract.py
prmpt/exceptions.py
prmpt/resolver.py
prmpt/validator.py
prmpt/integrations/__init__.py
prmpt/integrations/ollama.py
dotprmpt-0.1.0.dist-info/METADATA
dotprmpt-0.1.0.dist-info/WHEEL
dotprmpt-0.1.0.dist-info/entry_points.txt
dotprmpt-0.1.0.dist-info/top_level.txt
dotprmpt-0.1.0.dist-info/RECORD
