Metadata-Version: 2.4
Name: dotprmpt
Version: 0.1.0
Summary: System-enforced LLM contracts - define, validate, and enforce behavioral constraints on AI interactions
Author: Saurav Venkat
License: Apache-2.0
Project-URL: Homepage, https://github.com/sauravvenkat/prmpt
Project-URL: Documentation, https://github.com/sauravvenkat/prmpt#readme
Project-URL: Repository, https://github.com/sauravvenkat/prmpt
Project-URL: Issues, https://github.com/sauravvenkat/prmpt/issues
Keywords: llm,prompt,contract,validation,ai,specification,enforcement
Classifier: Development Status :: 3 - Alpha
Classifier: Intended Audience :: Developers
Classifier: License :: OSI Approved :: Apache Software License
Classifier: Operating System :: OS Independent
Classifier: Programming Language :: Python :: 3
Classifier: Programming Language :: Python :: 3.9
Classifier: Programming Language :: Python :: 3.10
Classifier: Programming Language :: Python :: 3.11
Classifier: Programming Language :: Python :: 3.12
Classifier: Topic :: Scientific/Engineering :: Artificial Intelligence
Classifier: Topic :: Software Development :: Libraries :: Python Modules
Classifier: Typing :: Typed
Requires-Python: >=3.9
License-File: LICENSE
Requires-Dist: pyyaml>=6.0
Provides-Extra: dev
Requires-Dist: pytest>=7.0; extra == "dev"
Requires-Dist: pytest-cov>=4.0; extra == "dev"
Requires-Dist: mypy>=1.0; extra == "dev"
Requires-Dist: ruff>=0.1.0; extra == "dev"
Provides-Extra: ollama
Dynamic: license-file
